contributed/__init__.py
contributed/batch_represent.py
contributed/cluster.py
contributed/clustering.py
contributed/export_embeddings.py
contributed/face.py
contributed/predict.py
contributed/real_time_face_recognition.py
facenet/__init__.py
facenet/src/__init__.py
facenet/src/calculate_filtering_metrics.py
facenet/src/classifier.py
facenet/src/compare.py
facenet/src/decode_msceleb_dataset.py
facenet/src/download_and_extract.py
facenet/src/face.py
facenet/src/facenet.py
facenet/src/freeze_graph.py
facenet/src/lfw.py
facenet/src/train_softmax.py
facenet/src/train_tripletloss.py
facenet/src/validate_on_lfw.py
facenet/src/align/__init__.py
facenet/src/align/align_dataset_mtcnn.py
facenet/src/align/det1.npy
facenet/src/align/det2.npy
facenet/src/align/det3.npy
facenet/src/align/detect_face.py
facenet/src/generative/__init__.py
facenet/src/generative/calculate_attribute_vectors.py
facenet/src/generative/modify_attribute.py
facenet/src/generative/train_vae.py
facenet/src/generative/models/__init__.py
facenet/src/generative/models/dfc_vae.py
facenet/src/generative/models/dfc_vae_large.py
facenet/src/generative/models/dfc_vae_resnet.py
facenet/src/generative/models/vae_base.py
facenet/src/models/__init__.py
facenet/src/models/dummy.py
facenet/src/models/inception_resnet_v1.py
facenet/src/models/inception_resnet_v2.py
facenet/src/models/squeezenet.py
tmp/__init__.py
tmp/align_dataset.py
tmp/align_dlib.py
tmp/cacd2000_split_identities.py
tmp/dataset_read_speed.py
tmp/deepdream.py
tmp/download_vgg_face_dataset.py
tmp/funnel_dataset.py
tmp/mnist_center_loss.py
tmp/mnist_noise_labels.py
tmp/mtcnn.py
tmp/mtcnn_test.py
tmp/mtcnn_test_pnet_dbg.py
tmp/network.py
tmp/nn2.py
tmp/nn3.py
tmp/nn4.py
tmp/nn4_small2_v1.py
tmp/random_test.py
tmp/rename_casia_directories.py
tmp/seed_test.py
tmp/select_triplets_test.py
tmp/test1.py
tmp/test_align.py
tmp/test_invariance_on_lfw.py
tmp/vggface16.py
tmp/vggverydeep19.py
tmp/visualize.py
tmp/visualize_vgg_model.py
tmp/visualize_vggface.py
facenet-1.0.4.dist-info/LICENSE.md
facenet-1.0.4.dist-info/METADATA
facenet-1.0.4.dist-info/WHEEL
facenet-1.0.4.dist-info/top_level.txt
facenet-1.0.4.dist-info/RECORD
